mabokahflib/__init__.py
mabokahflib/myfunctions.py
tests/__init__.py
tests/test_myfunctions.py
mabokahflib-0.1.1.dist-info/METADATA
mabokahflib-0.1.1.dist-info/WHEEL
mabokahflib-0.1.1.dist-info/top_level.txt
mabokahflib-0.1.1.dist-info/RECORD
