Metadata-Version: 2.1
Name: mabokahflib
Version: 0.1.1
Summary: My first Python library
Home-page: UNKNOWN
Author: Mohamed abokahf
License: UNKNOWN
Platform: UNKNOWN
